homeharvest/__init__.py
homeharvest/core/__init__.py
homeharvest/core/scrapers/__init__.py
homeharvest/core/scrapers/models.py
homeharvest/core/scrapers/realtor/__init__.py
homeharvest/core/scrapers/realtor/introspection.json
homeharvest/core/scrapers/realtor/parsers.py
homeharvest/core/scrapers/realtor/processors.py
homeharvest/core/scrapers/realtor/queries.py
homeharvest/exceptions.py
homeharvest/utils.py
homeharvest-0.8.18.dist-info/METADATA
homeharvest-0.8.18.dist-info/WHEEL
homeharvest-0.8.18.dist-info/licenses/LICENSE
homeharvest-0.8.18.dist-info/RECORD
